Workbook

Sheet Summary
A1: ELIIY Power (Japan) – Product, Application & Cost Benchmark
A2: Prepared 26 Oct 2026. Tabs: Product Specs · Where Used · Price Comparison · Market Benchmarks · Assumptions · Sources
B4: Key figure | C4: Value | D4: Comment
B5: Product families | C5: 4 | D5: LFP cells · motorcycle starters · home/office ESS · C&I ESS
B6: Active products listed | C6: =COUNTIF('Product Specs'!E5:E22,"Current*") -> 14 | D6: Plus custom 270 kWh build; 4 end-of-life lines
B7: POWER YIILE 3 – price (₹) | C7: ='Price Comparison'!H7 -> 670097.12 | D7: ¥1,097,800 retail incl. tax, converted at Assumptions FX
B8: POWER YIILE 3 – ₹/kWh | C8: ='Price Comparison'!I7 -> 268038.85 | D8: Premium, Japan-made, 12,000-cycle, SiC inverter
B9: Chinese OEM portable ESS – ₹/kWh (est.) | C9: ='Price Comparison'!V7 -> 19356 | D9: Factory ODM estimate
B10: ELIIY vs Chinese portable (x) | C10: ='Price Comparison'!X7 -> 13.847843 | D10: How many times costlier ELIIY is
B11: Home 5 kWh – India ₹/kWh | C11: ='Price Comparison'!O9 -> 23611.111 | D11: Luminous / Exide LFP, retail range mid
B12: Home 5 kWh – China ₹/kWh | C12: ='Price Comparison'!V9 -> 14299.783 | D12: Factory price, MOQ 100+
B13: C&I ESS – India ₹/kWh | C13: ='Price Comparison'!O11 -> 30000 | D13: Turnkey 1 MWh
B14: C&I ESS – China ₹/kWh | C14: ='Price Comparison'!V11 -> 7742.4 | D14: System price, ex-works
B15: HY93-C starter vs Indian lead-acid (x) | C15: ='Price Comparison'!Y5 -> 14.99806 | D15: ELIIY Li-ion vs Exide VRLA 7 Ah
B17: Takeaways
B18: 1. ELIIY's edge is safety and life, not price: cells pass nail/crush with no fire, rated 17,000 cycles to 70%, and carry 15-yr warranties.
B19: 2. On cost it is far above both India and China – POWER YIILE 3 is roughly an order of magnitude dearer per kWh than Chinese ODM portable units.
B20: 3. Motorcycle starters are its main OEM foothold (Honda, Suzuki); in India 2W OEMs still fit lead-acid at ~₹1,400–2,000 per unit.
B21: 4. Indian C&I storage (≈₹30k/kWh turnkey) is still ~3–4x Chinese ex-works system prices, largely because cells are imported.
B22: 5. Yellow cells in Price Comparison are estimates – confirm with supplier RFQs before using in a should-cost.

Sheet Assumptions
A1: Assumptions – Exchange Rates
A2: Blue = editable input. Change these and every ₹ figure in the workbook updates.
A4: Item | B4: Value | C4: Unit | D4: Source / note
A5: USD → INR | B5: 96.78 | C5: ₹ per USD | D5: banklive.net mid-market, 10 Oct 2026 (S40)
A6: JPY → INR | B6: 0.6104 | C6: ₹ per JPY | D6: banklive.net mid-market, 10 Oct 2026 (S40)
A7: USD → CNY | B7: 7.14 | C7: CNY per USD | D7: Implied by InfoLink: CNY 0.300/Wh ≈ $42/kWh (S33)
A8: EUR → USD | B8: 1.09 | C8: USD per EUR | D8: ESTIMATE – verify before use
A10: FX lookup table (used by formulas)
A11: Currency | B11: ₹ per 1 unit
A12: INR | B12: =1 -> 1
A13: USD | B13: =B5 -> 96.78
A14: JPY | B14: =B6 -> 0.6104
A15: CNY | B15: =B5/B7 -> 13.554622
A16: EUR | B16: =B8*B5 -> 105.4902

Sheet Product Photos
A1: ELIIY Power – Product Photos
A2: Official ELIIY Power images, loaded live with =IMAGE() (Excel 365 / Excel web / Excel mobile). Other apps show the link – tap it to view.
A4: Product | B4: Photo | C4: Category | D4: Official image link | E4: Product page
A5: HY battEliiy P-series (HY85S / HY93-C / HY110) | B5: =IFERROR(_xlfn.IMAGE("https://d1m4n9ip7tzk2j.cloudfront.net/tenants/1/item_field_asset_images/assets/000/002/114/large/0134595f-0aa3-4f1c-bee5-bf7e78b01460.jpg","HY battEliiy P-series (HY85S / HY93-C / HY110)",0),"Photo loads in Excel 365 – use link →") -> Photo loads in Excel 365 – use link → | C5: Motorcycle starter | D5: View photo | E5: Product page
A6: HY battEliiy P-series (lineup banner) | B6: =IFERROR(_xlfn.IMAGE("https://d1m4n9ip7tzk2j.cloudfront.net/tenants/1/additional_values/value_images/000/034/269/large/aba91e91-d5e3-4178-abee-f0d16db39cfd.jpg","HY battEliiy P-series (lineup banner)",0),"Photo loads in Excel 365 – use link →") -> Photo loads in Excel 365 – use link → | C6: Motorcycle starter | D6: View photo | E6: Product page
A7: HY93SS / HY110SS (Suzuki) | B7: =IFERROR(_xlfn.IMAGE("https://d1m4n9ip7tzk2j.cloudfront.net/tenants/1/additional_values/value_images/000/032/547/large/ae3b31ec-3ad7-4f01-9fd4-3df615c4fe42.jpg","HY93SS / HY110SS (Suzuki)",0),"Photo loads in Excel 365 – use link →") -> Photo loads in Excel 365 – use link → | C7: Motorcycle starter | D7: View photo | E7: Product page
A8: Charger C-1401B | B8: =IFERROR(_xlfn.IMAGE("https://d1m4n9ip7tzk2j.cloudfront.net/tenants/1/item_field_asset_images/assets/000/002/119/large/2cd285d1-9543-42f8-a836-78f3090f1bba.jpg","Charger C-1401B",0),"Photo loads in Excel 365 – use link →") -> Photo loads in Excel 365 – use link → | C8: Accessory | D8: View photo | E8: Product page
A9: POWER YIILE 3 | B9: =IFERROR(_xlfn.IMAGE("https://d1m4n9ip7tzk2j.cloudfront.net/tenants/1/additional_values/value_images/000/017/956/large/40a8f966-4120-45f3-9cdd-0b6d7da634b7.jpg","POWER YIILE 3",0),"Photo loads in Excel 365 – use link →") -> Photo loads in Excel 365 – use link → | C9: Portable indoor ESS | D9: View photo | E9: Product page
A10: POWER iE5 GRID | B10: =IFERROR(_xlfn.IMAGE("https://d1m4n9ip7tzk2j.cloudfront.net/tenants/1/additional_values/value_images/000/017/878/large/1e560fde-912a-4268-a3bb-f6be98abb2e4.jpg","POWER iE5 GRID",0),"Photo loads in Excel 365 – use link →") -> Photo loads in Excel 365 – use link → | C10: Home hybrid ESS | D10: View photo | E10: Product page
A11: 270 kWh custom system | B11: =IFERROR(_xlfn.IMAGE("https://d1m4n9ip7tzk2j.cloudfront.net/tenants/1/additional_values/value_images/000/017/984/large/cdc64889-bd4c-4259-9339-66f482c1585e.jpg","270 kWh custom system",0),"Photo loads in Excel 365 – use link →") -> Photo loads in Excel 365 – use link → | C11: Large custom ESS | D11: View photo | E11: Product page
A12: Power Storager 10 (end-of-life) | B12: =IFERROR(_xlfn.IMAGE("https://d1m4n9ip7tzk2j.cloudfront.net/tenants/1/additional_values/value_images/000/017/930/large/4605120e-cdee-4d35-b5a1-0a40a52abc23.jpg","Power Storager 10 (end-of-life)",0),"Photo loads in Excel 365 – use link →") -> Photo loads in Excel 365 – use link → | C12: C&I ESS | D12: View photo | E12: Product page
A13: ELIIY ONE (end-of-life) | B13: =IFERROR(_xlfn.IMAGE("https://d1m4n9ip7tzk2j.cloudfront.net/tenants/1/additional_values/value_images/000/017/917/large/4972fc1e-c3ac-446f-a717-d5bbb7b25d79.jpg","ELIIY ONE (end-of-life)",0),"Photo loads in Excel 365 – use link →") -> Photo loads in Excel 365 – use link → | C13: Portable power bank | D13: View photo | E13: Product page
A15: No official photos online for HEYA, Power Storager GX / X / D20 or the L-series cell – see their catalogues in the Sources tab.

Sheet Product Specs
A1: ELIIY Power – Product Specifications
A2: All from ELIIY Power product pages, catalogues and press releases. Cell chemistry across the range: LFP (lithium iron phosphate).
A4: # | B4: Product | C4: Model no. | D4: Category | E4: Status | F4: Capacity | G4: Usable / note | H4: Voltage | I4: Rated output | J4: Other output / CCA | K4: Charge time | L4: Run time at rated | M4: Size W×D×H (mm) | N4: Weight | O4: Operating temp | P4: Life / warranty | Q4: Key features | R4: Source
A5: 1 | B5: HY battEliiy L-series cell | C5: PD50S06 | D5: Battery cell | E5: Current | F5: ≈155 Wh (≈48.5 Ah × 3.2 V) | G5: Derived: 1C = 48.5 A; 1 cell = 155 Wh in ELIIY ONE | H5: 3.2 V nominal (LFP) | I5: 1C = 48.5 A | J5: — | K5: — | L5: — | M5: — | N5: — | O5: −20 to 60 °C | P5: 17,000 cycles to 70% (1C, 3 cyc/day, 15 yrs); >80% at 12,000 cycles | Q5: TÜV-S certified (first large Li-ion cell); no smoke/fire on nail & crush test; made in Kawasaki | R5: S10, S17, S19
A6: 2 | B6: HY battEliiy P-series | C6: HY85S | D6: Motorcycle starter | E6: Current | F6: 2.0 Ah (≈24 Wh) | G6: — | H6: 12 V | I6: — | J6: CCA ≥55 A | K6: — | L6: — | M6: 112 × 49 × 85 | N6: 0.7 kg | O6: −10 to 65 °C | P6: 100,000+ start cycles (in-house test) | Q6: Built-in BMU, PPS resin case; starts at −10 °C; very low self-discharge | R6: S2
A7: 3 | B7: HY battEliiy P-series | C7: HY93-C | D7: Motorcycle starter | E7: Current | F7: 4.5 Ah (≈54 Wh) | G7: — | H7: 12 V | I7: — | J7: CCA ≥110 A | K7: — | L7: — | M7: 112 × 70 × 93 | N7: 1.1 kg | O7: −10 to 65 °C | P7: 100,000+ start cycles | Q7: For 3+ cylinder bikes with 13.8–14.7 V charging | R7: S2, S4
A8: 4 | B8: HY battEliiy P-series | C8: HY110 | D8: Motorcycle starter | E8: Current | F8: 6.0 Ah (≈72 Wh) | G8: — | H8: 12 V | I8: — | J8: CCA ≥120 A | K8: — | L8: — | M8: 112 × 70 × 110 | N8: 1.4 kg | O8: −10 to 65 °C | P8: 100,000+ start cycles | Q8: Designated charger C-1401B | R8: S2, S4
A9: 5 | B9: HY battEliiy P-series (Suzuki) | C9: HY93SS | D9: Motorcycle starter | E9: Current (2025) | F9: 4.5 Ah (≈54 Wh) | G9: — | H9: 12 V | I9: — | J9: CCA 100 A | K9: — | L9: — | M9: 112 × 70 × 85 | N9: 0.9 kg | O9: −10 to 65 °C | P9: 100,000+ start cycles | Q9: BMU-less 'SyncCell' self-balancing electrolyte; replaceable fuse SBFW-L(M6) | R9: S3
A10: 6 | B10: HY battEliiy P-series (Suzuki) | C10: HY110SS | D10: Motorcycle starter | E10: Current | F10: 6.0 Ah (≈72 Wh) | G10: — | H10: 12 V | I10: — | J10: CCA 120 A | K10: — | L10: — | M10: 112 × 70 × 110 | N10: 1.24 kg | O10: −10 to 65 °C | P10: 100,000+ start cycles | Q10: SyncCell, replaceable fuse | R10: S3
A11: 7 | B11: POWER YIILE 3 | C11: PPS-30 | D11: Portable indoor ESS | E11: Current | F11: 2.5 kWh | G11: Plug-in, not grid-tied | H11: AC 100 V in/out | I11: 1.5 kVA / 1.4 kW | J11: Solar input (direct) | K11: ≈4 h (≈2 h fast mode) | L11: ≈90 min | M11: 320 × 585 × 514 | N11: 52 kg | O11: −10 to 40 °C | P11: 12,000 cycles; 10-yr warranty; 10-yr use limit | Q11: SiC power devices, 38 dB, ELIIY CLOUD remote monitoring, no installation work | R11: S5, S6
A12: 8 | B12: POWER YIILE HEYA | C12: PPS-40 | D12: Wall-mount indoor ESS | E12: Current | F12: 1.3 kWh | G12: 1.1 kWh effective (JEM1511) | H12: AC 101 V | I12: 500 VA / 500 W | J12: — | K12: ≈3 h | L12: ≈120 min | M12: 650 × 150 × 390 | N12: ≈30 kg | O12: — | P12: — | Q12: For apartments; LTE + Bluetooth monitoring; ~15 s switchover | R12: S8
A13: 9 | B13: POWER YIILE HEYA S | C13: PPS-40 | D13: Portable indoor ESS | E13: Current | F13: 1.3 kWh | G13: 1.1 kWh effective | H13: AC 101 V | I13: 500 VA / 500 W | J13: — | K13: ≈3 h | L13: ≈120 min | M13: 658 × 270 × 472 | N13: ≈40 kg | O13: — | P13: 10-yr warranty | Q13: ≈0.004 s switchover (not a UPS); 38 dB | R13: S9
A14: 10 | B14: POWER iE5 GRID (1 unit) | C14: EPS-40S | D14: Home hybrid ESS (whole-house) | E14: Current | F14: 5.4 kWh | G14: 4.9 kWh effective | H14: 202 V / 101 V | I14: Grid 8.4 kVA (8.0 kW) | J14: Backup 5.5 kVA; PV in 8.6 kW, 4 strings, MPPT 30–450 V | K14: ≈1–2 h | L14: ≈50 min | M14: Battery 610 × 300 × 991; PCS 445 × 198 × 698 | N14: 125 kg + 33 kg | O14: −20 to 45 °C (outdoor) | P14: 15-yr capacity (70%) + 15-yr system warranty | Q14: Full-load backup incl. 200 V appliances; Ene-Farm link; AI-SOLA cloud control | R14: S7
A15: 11 | B15: POWER iE5 GRID (2 units) | C15: EPS-40D | D15: Home hybrid ESS (whole-house) | E15: Current | F15: 10.8 kWh | G15: 2 battery units | H15: 202 V / 101 V | I15: Grid 8.4 kVA (8.0 kW) | J15: Backup 5.5 kVA | K15: ≈3–5 h | L15: ≈100 min | M15: 2 × battery units | N15: 2 × 125 kg + 33 kg | O15: −20 to 45 °C | P15: 15-yr warranties | Q15: Second unit can be added later | R15: S7
A16: 12 | B16: Power Storager GX | C16: — | D16: C&I ESS | E16: Current (Apr 2025) | F16: 22.5 – 1,006.3 kWh | G16: Modular | H16: 1-ph 202/101 V; 3-ph 202 / 420 / 440 V | I16: PCS 10 – 300 kW | J16: PV MPPT 15 – 450 kW | K16: — | L16: — | M16: Indoor / outdoor / salt-resistant cabinets | N16: — | O16: — | P16: Cell: 17,000 cycles to 70% | Q16: All-in-one PCS, DC-link PV converter, EMS, UPS switch, isolation transformer; 100% made in Japan | R16: S10, S20
... A22: 18 | B22: POWER iE6 / iE6 HYBRID | C22: — | D22: Home ESS / solar hybrid | E22: End-of-life | F22: 6.2 kWh | G22: — | H22: 100 V backup | I22: Battery out 2.0 kW, in 1.5 kW | J22: Integrated solar PCS (HYBRID) | K22: — | L22: — | M22: — | N22: — | O22: — | P22: — | Q22: Installed in all 66 homes of a Daiwa House smart town (Mie) | R22: S16
B24: Grey rows = discontinued. Wh for starter batteries = 12 V × Ah (nominal). PD50S06 capacity is derived from the 48.5 A (1C) test current, not a published datasheet value.

Sheet Where Used
A1: ELIIY Power – Where the Products Are Used
A2: Named OEMs and customers are those ELIIY Power or trade press have publicly disclosed.
A4: Product | B4: Segment | C4: Typical application | D4: Named OEMs / customers / sites | E4: Source
A5: HY85S | B5: Motorcycle OEM (Honda) | C5: Factory-fit starter on motocross race bikes | D5: Honda CRF250R, CRF450R, CRF450RX; Monster Energy Honda Team (Dakar Rally 2021 win) | E5: S2, S1
A6: HY93-C | B6: Motorcycle OEM + aftermarket | C6: Factory-fit starter on superbikes / off-road | D6: Honda CBR1000RR SP / SP2, CRF450L; sold in Japanese aftermarket from 2019 | E6: S2, S4
A7: HY110 | B7: Motorcycle OEM + aftermarket | C7: Factory-fit starter on adventure bikes | D7: Honda CRF1000L Africa Twin | E7: S2
A8: HY93SS | B8: Motorcycle OEM (Suzuki) | C8: Genuine-part starter | D8: Suzuki GSX-8T / GSX-8TT, GSX-R1000 / R1000R; Yoshimura SERT Motul endurance team | E8: S3
A9: HY110SS | B9: Motorcycle OEM (Suzuki) | C9: Genuine-part starter | D9: Suzuki Hayabusa | E9: S3
A10: POWER YIILE 3 | B10: Office BCP / public / home | C10: Plug-in emergency power for phones, PCs, lights, fridge | D10: NTT Docomo (~1,200 shops), Meiji Yasuda Life (102 branches), Daiwa House rental homes (every unit), 91 evacuation centres in Funabashi | E10: S21, S22, S23
A11: POWER YIILE HEYA / HEYA S | B11: Apartments / small offices | C11: Compact wall or floor backup for flats | D11: Multi-family housing; Good Design Best 100 (2019) | E11: S8, S9
A12: POWER iE5 GRID | B12: Detached homes | C12: Solar self-consumption + whole-house outage backup | D12: Japanese homes with rooftop PV; subsidy-eligible | E12: S7
A13: Power Storager GX / X / D20 | B13: Commercial & industrial | C13: Peak-cut, solar self-consumption, BCP, UPS | D13: Hanshin Tigers farm 'Zero Carbon Baseball Park', Benesse Style Care elder homes, Cosmo Oil R&D centre (demand response); 1 MWh at ELIIY Kawasaki plant | E13: S20, S10
A14: 270 kWh custom | B14: Industrial | C14: Critical-load backup for battery dry room | D14: ELIIY Power Kawasaki cell plant | E14: S14
A15: L-series cells / packs | B15: B2B cell supply | C15: Cells inside partner storage systems | D15: Enphase Energy AC Battery (8-cell 1.2 kWh modules); Daiwa House, Secom; Mazda / Ube joint work on car starter Li-ion | E15: S18, S17, S4
A16: Company | B16: Strategic | C16: Investor / partner | D16: Suzuki (additional investment & business alliance, Nov 2023); other shareholders incl. Daiwa House, Toray, Alps Alpine | E16: S42

Sheet Price Comparison
A1: ELIIY Power vs Indian OEM vs Chinese OEM – Rates
A2: Yellow rows/cells = estimate (no published figure found). Blue = hardcoded input. ₹ conversions use Assumptions sheet.
A4: # | B4: Category | C4: ELIIY model | D4: Capacity (kWh) | E4: ELIIY price | F4: ELIIY ccy | G4: ELIIY price basis | H4: ELIIY (₹) | I4: ELIIY ₹/kWh | J4: Indian OEM equivalent | K4: India low | L4: India high | M4: India ccy | N4: India mid (₹) | O4: India ₹/kWh | P4: India basis | Q4: Chinese OEM equivalent | R4: China low | S4: China high | T4: China ccy | U4: China mid (₹) | V4: China ₹/kWh | W4: China basis | X4: ELIIY ÷ China (x) | Y4: ELIIY ÷ India (x) | Z4: Sources
A5: 1 | B5: Motorcycle starter 12 V ~4.5 Ah | C5: HY93-C | D5: 0.054 | E5: 37790 | F5: JPY | G5: Japan aftermarket list, ex-tax (2019 launch) | H5: =IF(E5="","Quote only",E5*INDEX(Assumptions!$B$12:$B$16,MATCH(F5,Assumptions!$A$12:$A$16,0))) -> 23067.016 | I5: =IF(ISNUMBER(H5),H5/D5,"–") -> 427166.96 | J5: Lead-acid VRLA 7 Ah (Exide Bikerz) – what Indian 2W OEMs fit today | K5: 1386 | L5: 1690 | M5: INR | N5: =AVERAGE(K5:L5)*INDEX(Assumptions!$B$12:$B$16,MATCH(M5,Assumptions!$A$12:$A$16,0)) -> 1538 | O5: =N5/D5 -> 28481.481 | P5: Published dealer price (IndiaMART) | Q5: LiFePO4 starter 3–4 Ah, 180–240 CCA (e.g. Skyrich HJTX9/HJTZ10S class) | R5: 15 | S5: 25 | T5: USD | U5: =AVERAGE(R5:S5)*INDEX(Assumptions!$B$12:$B$16,MATCH(T5,Assumptions!$A$12:$A$16,0)) -> 1935.6 | V5: =U5/D5 -> 35844.444 | W5: ESTIMATE – factory FOB; EU dealer price for same class is €45–70 | X5: =IF(ISNUMBER(H5),H5/U5,"–") -> 11.917243 | Y5: =IF(ISNUMBER(H5),H5/N5,"–") -> 14.99806 | Z5: S4, S24, S25
A6: 2 | B6: Motorcycle starter 12 V ~6 Ah | C6: HY110 | D6: 0.072 | E6: 44460 | F6: JPY | G6: Japan aftermarket list, ex-tax (2019 launch) | H6: =IF(E6="","Quote only",E6*INDEX(Assumptions!$B$12:$B$16,MATCH(F6,Assumptions!$A$12:$A$16,0))) -> 27138.384 | I6: =IF(ISNUMBER(H6),H6/D6,"–") -> 376922 | J6: Lead-acid VRLA 9 Ah (Exide Bikerz 12BV9-B) | K6: 1800 | L6: 2045 | M6: INR | N6: =AVERAGE(K6:L6)*INDEX(Assumptions!$B$12:$B$16,MATCH(M6,Assumptions!$A$12:$A$16,0)) -> 1922.5 | O6: =N6/D6 -> 26701.389 | P6: Published dealer price (IndiaMART); low end estimated | Q6: LiFePO4 starter ~4–5 Ah, 240–290 CCA | R6: 20 | S6: 35 | T6: USD | U6: =AVERAGE(R6:S6)*INDEX(Assumptions!$B$12:$B$16,MATCH(T6,Assumptions!$A$12:$A$16,0)) -> 2661.45 | V6: =U6/D6 -> 36964.583 | W6: ESTIMATE – factory FOB; EU dealer €70–86 | X6: =IF(ISNUMBER(H6),H6/U6,"–") -> 10.196842 | Y6: =IF(ISNUMBER(H6),H6/N6,"–") -> 14.116195 | Z6: S4, S24, S25
A7: 3 | B7: Portable indoor ESS ~2.5 kWh | C7: POWER YIILE 3 | D7: 2.5 | E7: 1097800 | F7: JPY | G7: Retail incl. tax (BicCamera) | H7: =IF(E7="","Quote only",E7*INDEX(Assumptions!$B$12:$B$16,MATCH(F7,Assumptions!$A$12:$A$16,0))) -> 670097.12 | I7: =IF(ISNUMBER(H7),H7/D7,"–") -> 268038.85 | J7: Indian LFP 2.4–2.5 kWh module (Livguard / LOOM Atom class) – battery only | K7: 40000 | L7: 65000 | M7: INR | N7: =AVERAGE(K7:L7)*INDEX(Assumptions!$B$12:$B$16,MATCH(M7,Assumptions!$A$12:$A$16,0)) -> 52500 | O7: =N7/D7 -> 21000 | P7: Published price range (battery only; add inverter) | Q7: LiFePO4 portable power station ~2.5 kWh (OEM/ODM) | R7: 375 | S7: 625 | T7: USD | U7: =AVERAGE(R7:S7)*INDEX(Assumptions!$B$12:$B$16,MATCH(T7,Assumptions!$A$12:$A$16,0)) -> 48390 | V7: =U7/D7 -> 19356 | W7: ESTIMATE – $0.15–0.25/Wh factory; branded retail ≈$0.41/Wh (EcoFlow River 2 Pro) | X7: =IF(ISNUMBER(H7),H7/U7,"–") -> 13.847843 | Y7: =IF(ISNUMBER(H7),H7/N7,"–") -> 12.763755 | Z7: S5, S27, S28
A8: 4 | B8: Wall-mount indoor ESS ~1.3 kWh | C8: POWER YIILE HEYA | D8: 1.3 | F8: JPY | G8: Not published – quote only | H8: =IF(E8="","Quote only",E8*INDEX(Assumptions!$B$12:$B$16,MATCH(F8,Assumptions!$A$12:$A$16,0))) -> Quote only | I8: =IF(ISNUMBER(H8),H8/D8,"–") -> – | J8: Indian LFP ~1.3 kWh (pro-rata of ₹20k–35k/kWh) | K8: 26000 | L8: 45500 | M8: INR | N8: =AVERAGE(K8:L8)*INDEX(Assumptions!$B$12:$B$16,MATCH(M8,Assumptions!$A$12:$A$16,0)) -> 35750 | O8: =N8/D8 -> 27500 | P8: Derived from published ₹/kWh range | Q8: LiFePO4 wall battery ~1.3 kWh | R8: 180 | S8: 300 | T8: USD | U8: =AVERAGE(R8:S8)*INDEX(Assumptions!$B$12:$B$16,MATCH(T8,Assumptions!$A$12:$A$16,0)) -> 23227.2 | V8: =U8/D8 -> 17867.077 | W8: ESTIMATE – pro-rata of 5 kWh factory pricing | X8: =IF(ISNUMBER(H8),H8/U8,"–") -> – | Y8: =IF(ISNUMBER(H8),H8/N8,"–") -> – | Z8: S26, S29
A9: 5 | B9: Home hybrid ESS 5 kWh class | C9: POWER iE5 GRID (EPS-40S) | D9: 5.4 | F9: JPY | G9: Not published – dealer quote only | H9: =IF(E9="","Quote only",E9*INDEX(Assumptions!$B$12:$B$16,MATCH(F9,Assumptions!$A$12:$A$16,0))) -> Quote only | I9: =IF(ISNUMBER(H9),H9/D9,"–") -> – | J9: Luminous / Exide 5 kWh LFP | K9: 105000 | L9: 150000 | M9: INR | N9: =AVERAGE(K9:L9)*INDEX(Assumptions!$B$12:$B$16,MATCH(M9,Assumptions!$A$12:$A$16,0)) -> 127500 | O9: =N9/D9 -> 23611.111 | P9: Published price range, Jun 2026 | Q9: 51.2 V 5.12 kWh all-in-one wall unit (LiFePower ALW-5kW) | R9: 723 | S9: 741 | T9: EUR | U9: =AVERAGE(R9:S9)*INDEX(Assumptions!$B$12:$B$16,MATCH(T9,Assumptions!$A$12:$A$16,0)) -> 77218.826 | V9: =U9/D9 -> 14299.783 | W9: Published factory price, MOQ 100+ (ENF) | X9: =IF(ISNUMBER(H9),H9/U9,"–") -> – | Y9: =IF(ISNUMBER(H9),H9/N9,"–") -> – | Z9: S7, S26, S29
A10: 6 | B10: Home hybrid ESS 10 kWh class | C10: POWER iE5 GRID (EPS-40D) | D10: 10.8 | F10: JPY | G10: Not published – dealer quote only | H10: =IF(E10="","Quote only",E10*INDEX(Assumptions!$B$12:$B$16,MATCH(F10,Assumptions!$A$12:$A$16,0))) -> Quote only | I10: =IF(ISNUMBER(H10),H10/D10,"–") -> – | J10: Luminous / Exide 10 kWh LFP | K10: 200000 | L10: 290000 | M10: INR | N10: =AVERAGE(K10:L10)*INDEX(Assumptions!$B$12:$B$16,MATCH(M10,Assumptions!$A$12:$A$16,0)) -> 245000 | O10: =N10/D10 -> 22685.185 | P10: Published price range, Jun 2026 | Q10: 2 × 5.12 kWh wall units | R10: 1446 | S10: 1482 | T10: EUR | U10: =AVERAGE(R10:S10)*INDEX(Assumptions!$B$12:$B$16,MATCH(T10,Assumptions!$A$12:$A$16,0)) -> 154437.65 | V10: =U10/D10 -> 14299.783 | W10: Derived: 2 × published unit price | X10: =IF(ISNUMBER(H10),H10/U10,"–") -> – | Y10: =IF(ISNUMBER(H10),H10/N10,"–") -> – | Z10: S7, S26, S29
A11: 7 | B11: C&I ESS (per kWh, turnkey) | C11: Power Storager GX / X / D20 | D11: 1 | F11: JPY | G11: Not published – project quote | H11: =IF(E11="","Quote only",E11*INDEX(Assumptions!$B$12:$B$16,MATCH(F11,Assumptions!$A$12:$A$16,0))) -> Quote only | I11: =IF(ISNUMBER(H11),H11/D11,"–") -> – | J11: Indian 1 MWh C&I turnkey system | K11: 28000 | L11: 32000 | M11: INR | N11: =AVERAGE(K11:L11)*INDEX(Assumptions!$B$12:$B$16,MATCH(M11,Assumptions!$A$12:$A$16,0)) -> 30000 | O11: =N11/D11 -> 30000 | P11: Published: ₹2.8–3.2 cr per MWh, 2026 | Q11: Chinese C&I ESS (e.g. 261 kWh all-in-one cabinet) | R11: 70 | S11: 90 | T11: USD | U11: =AVERAGE(R11:S11)*INDEX(Assumptions!$B$12:$B$16,MATCH(T11,Assumptions!$A$12:$A$16,0)) -> 7742.4 | V11: =U11/D11 -> 7742.4 | W11: Published SMM range $0.07–0.09/Wh (BNEF avg $77/kWh) | X11: =IF(ISNUMBER(H11),H11/U11,"–") -> – | Y11: =IF(ISNUMBER(H11),H11/N11,"–") -> – | Z11: S30, S31, S32
A12: 8 | B12: LFP cells (per kWh) | C12: HY battEliiy L-series PD50S06 | D12: 1 | F12: JPY | G12: Not published | H12: =IF(E12="","Quote only",E12*INDEX(Assumptions!$B$12:$B$16,MATCH(F12,Assumptions!$A$12:$A$16,0))) -> Quote only | I12: =IF(ISNUMBER(H12),H12/D12,"–") -> – | J12: Landed LFP cell / pack procurement in India (mostly imported) | K12: 55 | L12: 75 | M12: USD | N12: =AVERAGE(K12:L12)*INDEX(Assumptions!$B$12:$B$16,MATCH(M12,Assumptions!$A$12:$A$16,0)) -> 6290.7 | O12: =N12/D12 -> 6290.7 | P12: Published: IESA $55–60, Crisil $70–75/kWh (2026) | Q12: Chinese LFP storage cells (100 Ah → 314 Ah) | R12: 360 | S12: 443 | T12: CNY | U12: =AVERAGE(R12:S12)*INDEX(Assumptions!$B$12:$B$16,MATCH(T12,Assumptions!$A$12:$A$16,0)) -> 5442.1807 | V12: =U12/D12 -> 5442.1807 | W12: Published: CNY 0.360–0.443/Wh, Jul 2026 | X12: =IF(ISNUMBER(H12),H12/U12,"–") -> – | Y12: =IF(ISNUMBER(H12),H12/N12,"–") -> – | Z12: S33, S34, S35, S36
B14: Notes
B15: • 'Indian OEM' for starters = lead-acid VRLA, because Indian 2-wheeler OEMs still factory-fit lead-acid; no published Indian OEM rate for Li-ion starters was found.
B16: • Indian per-kWh figures are battery-only unless stated; ELIIY units include inverter/PCS, so like-for-like gap is somewhat smaller than shown.
B17: • ELIIY sells mainly in Japan; prices for iE5 GRID, HEYA, GX/X/D20 and cells are quote-only. Rows show India vs China only for those.
B18: • Starter-battery ₹/kWh is shown for completeness; compare starters per unit (CCA, weight, life), not per kWh.
B21: Chart data – storage ₹/kWh (India vs China)
B22: Category | C22: India ₹/kWh | D22: China ₹/kWh
B23: Portable ~2.5 kWh | C23: =O7 -> 21000 | D23: =V7 -> 19356
B24: Home 5 kWh | C24: =O9 -> 23611.111 | D24: =V9 -> 14299.783
B25: Home 10 kWh | C25: =O10 -> 22685.185 | D25: =V10 -> 14299.783
B26: C&I turnkey | C26: =O11 -> 30000 | D26: =V11 -> 7742.4
B27: LFP cells | C27: =O12 -> 6290.7 | D27: =V12 -> 5442.1807
B29: ELIIY POWER YIILE 3 for reference (₹/kWh): | C29: =I7 -> 268038.85

Sheet Market Benchmarks
A1: Battery & BESS Price Benchmarks – India vs China (2025–26)
A2: Context for OEM rates above. Blue = published figure.
A4: Market | B4: Metric | C4: Value | D4: Unit | E4: ₹ equivalent | F4: ₹ unit | G4: Date | H4: Source
A5: China | B5: 314 Ah LFP storage cell (InfoLink avg) | C5: 0.365 | D5: CNY/Wh | E5: =C5*1000*Assumptions!$B$15 -> 4947.437 | F5: ₹/kWh | G5: Apr 2026 | H5: S33
A6: China | B6: 280/314 Ah LFP storage cell (tax-incl.) | C6: 0.36 | D6: CNY/Wh | E6: =C6*1000*Assumptions!$B$15 -> 4879.6639 | F6: ₹/kWh | G6: Jul 2026 | H6: S34
A7: China | B7: 100 Ah LFP cell | C7: 0.443 | D7: CNY/Wh | E7: =C7*1000*Assumptions!$B$15 -> 6004.6975 | F7: ₹/kWh | G7: Jul 2026 | H7: S34
A8: China | B8: 2-h DC-side liquid-cooled ESS (avg) | C8: 0.49 | D8: CNY/Wh | E8: =C8*1000*Assumptions!$B$15 -> 6641.7647 | F8: ₹/kWh | G8: Apr 2026 | H8: S33
A9: China | B9: C&I ESS system (SMM avg) | C9: 80 | D9: USD/kWh | E9: =C9*Assumptions!$B$13 -> 7742.4 | F9: ₹/kWh | G9: Dec 2025 | H9: S31
A10: China | B10: C&I / data-centre turnkey (BNEF avg) | C10: 77 | D10: USD/kWh | E10: =C10*Assumptions!$B$13 -> 7452.06 | F10: ₹/kWh | G10: 2025 | H10: S32
A11: China | B11: Utility turnkey ESS (BNEF avg) | C11: 66 | D11: USD/kWh | E11: =C11*Assumptions!$B$13 -> 6387.48 | F11: ₹/kWh | G11: 2025 | H11: S32
A12: China | B12: Grid-scale EPC, 4-h (avg winning bid) | C12: 140 | D12: USD/kWh | E12: =C12*Assumptions!$B$13 -> 13549.2 | F12: ₹/kWh | G12: Q1 2026 | H12: S41
A13: India | B13: Battery procurement price (Crisil) | C13: 72.5 | D13: USD/kWh | E13: =C13*Assumptions!$B$13 -> 7016.55 | F13: ₹/kWh | G13: 2026 | H13: S35
A14: India | B14: Battery price (IESA) | C14: 57.5 | D14: USD/kWh | E14: =C14*Assumptions!$B$13 -> 5564.85 | F14: ₹/kWh | G14: Jun 2026 | H14: S36
A15: India | B15: LFP home battery (retail range mid) | C15: 27500 | D15: INR/kWh | E15: =C15 -> 27500 | F15: ₹/kWh | G15: 2026 | H15: S26
A16: India | B16: C&I 1 MWh turnkey (mid of ₹2.8–3.2 cr) | C16: 30000 | D16: INR/kWh | E16: =C16 -> 30000 | F16: ₹/kWh | G16: 2026 | H16: S30
A17: India | B17: Standalone BESS tariff, 4-h (Rajasthan L1) | C17: 285000 | D17: INR/MW/month | E17: =C17 -> 285000 | F17: ₹/MW/month | G17: Nov 2025 | H17: S38
A18: India | B18: Standalone BESS tariff, 2-h (Kerala L1) | C18: 181000 | D18: INR/MW/month | E18: =C18 -> 181000 | F18: ₹/MW/month | G18: Jan 2026 | H18: S37
A19: India | B19: Standalone BESS tariff, 2-h (lowest L1 tracked) | C19: 148000 | D19: INR/MW/month | E19: =C19 -> 148000 | F19: ₹/MW/month | G19: May 2026 | H19: S39

Sheet Sources
A1: Sources
A3: ID | B3: Description | C3: URL
A4: S1 | B4: ELIIY Power – English home & news (Dakar 2021, Suzuki alliance) | C4: https://www.eliiypower.co.jp/english
A5: S2 | B5: HY battEliiy P-series spec page | C5: https://www.eliiypower.co.jp/english/products-en/motorcycle-en/hybattery-p-en
A6: S3 | B6: HY battEliiy P-series – Suzuki models (HY93SS / HY110SS) | C6: https://www.eliiypower.co.jp/english/products-en/motorcycle-en/hybattery-p2-en
A7: S4 | B7: MONOist – HY93-C / HY110 aftermarket launch & prices (Mar 2019) | C7: https://monoist.itmedia.co.jp/mn/articles/1903/25/news050.html
A8: S5 | B8: BicCamera – POWER YIILE 3 PPS-30 price & specs | C8: https://www.biccamera.com/bc/item/6450611/
A9: S6 | B9: Taiyoko-kakaku – POWER YIILE 3 specs (cycles, size, weight) | C9: https://www.taiyoko-kakaku.jp/product/eliiypower3
A10: S7 | B10: POWER iE5 GRID catalogue (PDF) | C10: https://www.eliiypower.co.jp/files/pdf/catalog_PiE5G.pdf
A11: S8 | B11: POWER YIILE HEYA press release (Jul 2019) | C11: https://www.eliiypower.co.jp/files/pdf/20190726.pdf
A12: S9 | B12: POWER YIILE HEYA S press release (Aug 2019) | C12: https://www.eliiypower.co.jp/files/pdf/20190830.pdf
A13: S10 | B13: Power Storager GX catalogue (Feb 2025) | C13: https://eliiypower.co.jp/files/pdf/catalog_PS-GX_202502.pdf
A14: S11 | B14: Power Storager X catalogue | C14: https://www.eliiypower.co.jp/files/pdf/catalog_PowerStragerX.pdf
... A45: S42 | B45: ELIIY Power & Suzuki investment / alliance (Nov 2023) | C45: https://www.eliiypower.co.jp/english/pressrelease-en/20231114_e

Sheet How Prices Were Got
A1: How the Prices Were Obtained
A3: Column | B3: Method | C3: Confidence
A4: ELIIY prices | B4: Only two public price points exist. POWER YIILE 3: retail listing on BicCamera.com (¥1,097,800 incl. tax). HY93-C / HY110: Japanese launch list prices reported by MONOist, 2019 (¥37,790 / ¥44,460 ex-tax). All other ELIIY products are sold on quotation only. | C4: High (list)
A5: Indian OEM – starters | B5: Exide Bikerz VRLA dealer prices on IndiaMART (₹1,386–2,045). Used because Indian 2W OEMs still factory-fit lead-acid; no Indian Li-ion OEM starter rate is published. | C5: Medium
A6: Indian OEM – home ESS | B6: Published 2026 price ranges for Luminous / Exide 5 and 10 kWh LFP (QuickEstimate) and Livguard / LOOM 2.4 kWh modules (Qbits Energy). These are distributor/retail ranges, not OEM contract rates. | C6: Medium
A7: Indian OEM – C&I and cells | B7: C&I: ₹2.8–3.2 cr per MWh turnkey (DCNT Global 2026 buyer's guide). Cells: landed battery prices from IESA ($55–60/kWh) and Crisil ($70–75/kWh). | C7: Medium
A8: Chinese OEM – home ESS | B8: Factory price list on ENF Solar for a 5.12 kWh all-in-one unit: €741 (100–199 pcs), €723 (200+ pcs). | C8: High (list)
A9: Chinese OEM – C&I and cells | B9: SMM price index ($0.07–0.09/Wh C&I systems), BNEF survey ($77/kWh), InfoLink and ECOinfos cell indices (CNY 0.360–0.443/Wh). | C9: High (index)
A10: Chinese OEM – starters & portable | B10: ESTIMATES (yellow). No public factory price found. Based on EU dealer prices for Chinese-made Skyrich LiFePO4 starters (€45–86) and EcoFlow retail (~$0.41/Wh), discounted to typical factory FOB levels. | C10: Low – RFQ needed
A11: Currency | B11: Mid-market FX on 10 Oct 2026 (banklive.net). Change the yellow cells on the Assumptions tab to re-price everything. | C11: High
